{
  "source": "小红书种草学（官方营销学习平台）",
  "url": "https://xue.xiaohongshu.com/home",
  "layer": "C",
  "loginAccount": "Savey（小红书商业化账号，已登录）",
  "collectDate": "2026-07-16",
  "dataUpdateTime": "2026-07-16 15:38",
  "collectionDepth": 2,
  "depthNote": "公开层可见课程/直播/讲师/学习地图等定性信息；家居家装行业的量化榜单（笔记/爆文/达人/品牌流量大盘）位于千帆推广/蒲公英后台的『数据洞察-行业洞察-报告中心』，需对应商业产品账号权限，本账号未开通，量化数据未取。",
  "note": "本源为营销学习/方法论平台，非天猫竞品交易数据源。价值在于印证小红书对家装赛道的官方运营重视度与内容打法，供社媒种草侧参考，不作为交易份额类硬指标。",
  "qualitative": {
    "homeIndustryIsKeyVertical": true,
    "evidence": [
      "平台『行业应用』标准分类中，『家具家装』位列首位（家具家装/影像婚美/医美/互联网/文旅）",
      "『认证讲师』中多位明星讲师主攻家居家装赛道：九千（深圳非池传媒创始人，家居家装+服饰鞋包）、李逸凡（曼拾创始人，食品饮料+家居家装+3C电器）、潘小双（馒头商学院导师，教育培训+家居家装+文旅餐饮）、吴雨晨（尔元传媒创始人，家居家装+教育培训+文旅影美，单月获客7000+）",
      "存在『账号装修号广同开』等家装商家专项产品能力路径",
      "近期直播：2026-07-20 13:30 『家装&金融行业 KOS内容实践』"
    ],
    "recentLiveSchedule": [
      {"title": "家装&金融行业 KOS内容实践", "time": "2026-07-20 13:30:00", "status": "未开始/可预约"},
      {"title": "到综行业 KOS+企业号内容实践", "time": "2026-07-20 16:45:00"},
      {"title": "教育&影美行业 KOS内容实践", "time": "2026-07-21 13:30:00"},
      {"title": "二奢行业 KOS策略内容实践", "time": "2026-07-21 16:45:00"}
    ],
    "methodologyKeywords": ["KOS（企业员工号）内容实践", "KFS产品种草组合投放", "人群反漏斗模型", "小红书四级种草力", "SPU x 买点 x 人群", "双C计划全域种草", "种草直达CID投放SOP"]
  },
  "insights": [
    "小红书官方把『家具家装』列为行业应用第一类，且配置了4位以上专攻家装的明星讲师——印证家装是小红书重点招商与内容扶持赛道，天猫家装商家在社媒种草侧面临小红书的强势分流，应重点监控站外小红书种草对站内搜索/成交的引流关系。",
    "官方主推打法为 KOS（企业员工号矩阵）+ KFS 组合投放 + 人群反漏斗，7-20 专门开设家装 KOS 内容实践直播——建议天猫家装头部商家对标其 KOS 矩阵打法，评估店铺导购号在小红书的内容布局。",
    "家装量化流量大盘（笔记数/爆文/达人/品牌榜）在千帆/蒲公英后台，受账号权限限制未取；如需该口径数据，需用户提供已开通对应商业产品的账号，或改用蝉小红/千瓜会员版补充。"
  ],
  "blockers": "家居家装行业量化榜单需千帆/蒲公英商业产品账号权限，当前账号未开通；千瓜家居家装大盘为尊享版会员墙，已跳过。"
}
